{
  "success": true,
  "photocards": [
    {
      "id": "cmguyeqeb007pl504juohalm1",
      "name": "LE SSERAFIM - Kim Chaewon - FEARLESS Album",
      "group_id": "cmeqz8pd4002e136wxlrxz44a",
      "member_id": "cmeqz8pi7002i136wustcdcjw",
      "album_id": "cmgst9yhu0019le040ci81c7m",
      "review_status": "approved",
      "approvals_count": 0,
      "rejects_count": 0,
      "watermarked_image_url": "https://hywfhpjrxseqlrzqyghg.supabase.co/storage/v1/object/public/watermarked/cmguyeqeb007pl504juohalm1-front-1779187819351.webp",
      "watermarked_back_url": "https://hywfhpjrxseqlrzqyghg.supabase.co/storage/v1/object/public/watermarked/cmguyeqeb007pl504juohalm1-back-1766172246454.webp",
      "watermarked_at": "2026-05-19T10:50:21.820Z",
      "rarity": "common",
      "card_number": null,
      "is_group_pc": false,
      "origin": "Album",
      "source_url": null,
      "event_id": null,
      "created_at": "2025-10-17T14:38:27.108Z",
      "updated_at": "2026-03-16T22:42:29.737Z",
      "created_by": "cmgpl5bt10005jv04zfarw86v",
      "finish_type": "normal",
      "group": {
        "id": "cmeqz8pd4002e136wxlrxz44a",
        "name": "LE SSERAFIM",
        "korean_name": "르세라핌"
      },
      "member": {
        "id": "cmeqz8pi7002i136wustcdcjw",
        "name": "Kim Chaewon",
        "stage_name": "Kim Chaewon"
      },
      "album": {
        "id": "cmgst9yhu0019le040ci81c7m",
        "title": "FEARLESS",
        "korean_title": null
      },
      "event": null,
      "other": null,
      "creator": {
        "id": "cmgpl5bt10005jv04zfarw86v",
        "username": "keara",
        "name": "Keara",
        "avatar_url": "https://lh3.googleusercontent.com/a/ACg8ocKiO_4SQ9DpRGkaXatYQg4Sac2_jxKIB6MG805jTiJjoQMsfG2wpw=s96-c"
      },
      "tag_links": [
        {
          "id": "cmmtrr0fo005wla04bvqupw28",
          "tag_id": "cmgstaze70007js04ca7kcvd2",
          "photocard_id": "cmguyeqeb007pl504juohalm1",
          "created_at": "2026-03-16T22:42:30.517Z",
          "tag": {
            "name": "blue chypre version"
          }
        },
        {
          "id": "cmmtrr0fo005yla04ddwtvgvu",
          "tag_id": "cmg72zbso0001lg0f9un7ssi2",
          "photocard_id": "cmguyeqeb007pl504juohalm1",
          "created_at": "2026-03-16T22:42:30.517Z",
          "tag": {
            "name": "standard version"
          }
        },
        {
          "id": "cmmtrr0fo005zla04xmyvpfxy",
          "tag_id": "cmg2pj0bn0000uz9eyd1l9ahj",
          "photocard_id": "cmguyeqeb007pl504juohalm1",
          "created_at": "2026-03-16T22:42:30.517Z",
          "tag": {
            "name": "album photocard"
          }
        }
      ],
      "is_double_sided": false,
      "pending_edit_suggestions_count": 0,
      "tags": [
        "blue chypre version",
        "standard version",
        "album photocard"
      ],
      "listings": [
        {
          "id": "cmot64uc82cb4x0vx0wnfcsh8",
          "image_url": "https://u-mercari-images.mercdn.net/photos/m22500622331_1.jpg",
          "price_value": 8,
          "price_currency": "USD",
          "created_at": "2026-05-05T21:56:48.920Z"
        },
        {
          "id": "cmolzo1jjvlubdg616g0am911",
          "image_url": "https://u-mercari-images.mercdn.net/photos/m35525963725_1.jpg",
          "price_value": 13,
          "price_currency": "USD",
          "created_at": "2026-04-30T21:21:24.175Z"
        },
        {
          "id": "cmolvg6rvuzx1rgvv7m8ber1g",
          "image_url": "https://u-mercari-images.mercdn.net/photos/m72515923416_1.jpg",
          "price_value": 7.35,
          "price_currency": "USD",
          "created_at": "2026-04-30T19:23:19.243Z"
        },
        {
          "id": "cmofc0nstj80ehovwmm6dwyzy",
          "image_url": "https://u-mercari-images.mercdn.net/photos/m51080018892_1.jpg",
          "price_value": 9,
          "price_currency": "USD",
          "created_at": "2026-04-26T05:32:45.053Z"
        },
        {
          "id": "cmocnyx1pp961vgptp7ez60qw",
          "image_url": "https://u-mercari-images.mercdn.net/photos/m18598418988_1.jpg",
          "price_value": 11,
          "price_currency": "USD",
          "created_at": "2026-04-24T08:44:00.589Z"
        },
        {
          "id": "cmnpn84ni00fjisvv3bcewyn2",
          "image_url": "https://i.ebayimg.com/images/g/tRoAAOSwKZFmO~bl/s-l1600.jpg",
          "price_value": 14060.56,
          "price_currency": "KRW",
          "created_at": "2026-04-08T06:04:27.932Z"
        }
      ]
    }
  ],
  "total": 1351,
  "page": 1351,
  "pageSize": 1,
  "timestamp": "2026-05-23T22:45:22.902Z"
}
